[{"__symbolic":"module","version":3,"metadata":{"WidgetRegistry":{"__symbolic":"class","members":{"__ctor__":[{"__symbolic":"constructor"}],"setDefaultWidget":[{"__symbolic":"method"}],"getDefaultWidget":[{"__symbolic":"method"}],"hasWidget":[{"__symbolic":"method"}],"register":[{"__symbolic":"method"}],"getWidgetType":[{"__symbolic":"method"}]}}}},{"__symbolic":"module","version":1,"metadata":{"WidgetRegistry":{"__symbolic":"class","members":{"__ctor__":[{"__symbolic":"constructor"}],"setDefaultWidget":[{"__symbolic":"method"}],"getDefaultWidget":[{"__symbolic":"method"}],"hasWidget":[{"__symbolic":"method"}],"register":[{"__symbolic":"method"}],"getWidgetType":[{"__symbolic":"method"}]}}}}]